onedrivedownloader/__init__.py
onedrivedownloader/main.py
onedrivedownloader-1.1.3.dist-info/LICENSE.txt
onedrivedownloader-1.1.3.dist-info/METADATA
onedrivedownloader-1.1.3.dist-info/WHEEL
onedrivedownloader-1.1.3.dist-info/top_level.txt
onedrivedownloader-1.1.3.dist-info/RECORD
