Metadata-Version: 2.1
Name: onedrivedownloader
Version: 1.1.3
Summary: Python utility to download files through OneDrive
Home-page: https://github.com/loribonna/onedrivedownloader
Author: Lorenzo Bonicelli
Author-email: loribonna@gmail.com
License: MIT
Download-URL: https://github.com/loribonna/onedrivedownloader/archive/refs/tags/v1.1.3.zip
Keywords: onedrive,downloader,download,python,utility
Platform: UNKNOWN
Classifier: Development Status :: 3 - Alpha
Classifier: Intended Audience :: Developers
Classifier: Topic :: Software Development :: Build Tools
Classifier: License :: OSI Approved :: MIT License
Classifier: Programming Language :: Python :: 3
Classifier: Programming Language :: Python :: 3.7
Classifier: Programming Language :: Python :: 3.8
License-File: LICENSE.txt
